hwplib/__init__.py
hwplib/hwp3/__init__.py
hwplib/hwp3/parser_v3.py
hwplib/hwp5/__init__.py
hwplib/hwp5/api.py
hwplib/hwp5/chart/__init__.py
hwplib/hwp5/chart/chart_model.py
hwplib/hwp5/chart/chart_parser.py
hwplib/hwp5/core/__init__.py
hwplib/hwp5/core/body_text.py
hwplib/hwp5/core/control.py
hwplib/hwp5/core/doc_info.py
hwplib/hwp5/core/exporter.py
hwplib/hwp5/core/file_header.py
hwplib/hwp5/core/model.py
hwplib/hwp5/core/record.py
hwplib/hwp5/core/storage.py
hwplib/hwp5/distribute/__init__.py
hwplib/hwp5/distribute/distribute_handler.py
hwplib/hwp5/equation/__init__.py
hwplib/hwp5/equation/equation_parser.py
hwplib/hwp5/equation/equation_symbols.py
hwplib/hwp5/equation/equation_tokenizer.py
hwplib/hwpml/__init__.py
hwplib/hwpml/model_xml.py
hwplib/hwpx/__init__.py
hwplib/hwpx/api.py
hwplib/hwpx/model.py
hwplib_py-1.0.0.dist-info/licenses/LICENSE
hwplib_py-1.0.0.dist-info/METADATA
hwplib_py-1.0.0.dist-info/WHEEL
hwplib_py-1.0.0.dist-info/top_level.txt
hwplib_py-1.0.0.dist-info/RECORD
