Metadata-Version: 2.4
Name: hwplib-py
Version: 1.0.0
Summary: A pure Python parser for the HWP (Hangul Word Processor) 5.0 binary file format.
Author-email: CHoi Minseo <minseo0388@github.com>
Project-URL: Homepage, https://github.com/minseo0388/hwplib-py
Project-URL: Bug Tracker, https://github.com/minseo0388/hwplib-py/issues
Project-URL: Documentation, https://minseo0388.github.io/hwplib-py/
Keywords: hwp,hangul,parser,ole2,hwplib
Classifier: Programming Language :: Python :: 3
Classifier: License :: OSI Approved :: Apache Software License
Classifier: Operating System :: OS Independent
Classifier: Development Status :: 5 - Production/Stable
Classifier: Intended Audience :: Developers
Classifier: Topic :: Text Processing :: General
Requires-Python: >=3.7
License-File: LICENSE
Requires-Dist: olefile>=0.46
Dynamic: license-file
